chatterbox_wake_word_plugin_doubletaps
